decouplet/__init__.py
decouplet/config.py
decouplet/secrets.py
decouplet-0.1.4.dist-info/licenses/LICENSE
decouplet-0.1.4.dist-info/METADATA
decouplet-0.1.4.dist-info/WHEEL
decouplet-0.1.4.dist-info/top_level.txt
decouplet-0.1.4.dist-info/RECORD
