Metadata-Version: 2.4
Name: decouplet
Version: 0.1.4
Summary: Decouple config with support for secrets directory (e.g., Docker secrets)
Author-email: Kulbarakov Bakdoolot <kulbarakovbh@gmail.com>
License: MIT
Requires-Python: >=3.9
License-File: LICENSE
Requires-Dist: python-decouple>=3.8
Dynamic: license-file
